verlauf/__init__.py
verlauf/__main__.py
verlauf/gradients.py
verlauf/hex.py
verlauf/utils.py
verlauf-1.0.2.dist-info/LICENSE
verlauf-1.0.2.dist-info/METADATA
verlauf-1.0.2.dist-info/WHEEL
verlauf-1.0.2.dist-info/entry_points.txt
verlauf-1.0.2.dist-info/RECORD
