Metadata-Version: 2.1
Name: verlauf
Version: 1.0.2
Summary: Verlauf - The Terminal Color Gradient Generator
Home-page: https://gitlab.com/ceda_ei/verlauf.git
License: GPL-3.0
Author: Ceda EI
Author-email: ceda_ei@webionite.com
Requires-Python: >=3.8,<4.0
Classifier: License :: OSI Approved :: GNU General Public License v3 (GPLv3)
Classifier: Programming Language :: Python :: 3
Classifier: Programming Language :: Python :: 3.8
Classifier: Programming Language :: Python :: 3.9
Classifier: Programming Language :: Python :: 3.10
Classifier: Programming Language :: Python :: 3.11
Requires-Dist: click (>=8.0.1,<9.0.0)
Project-URL: Repository, https://gitlab.com/ceda_ei/verlauf.git
